MANIFEST.in
README.txt
bootstrap.py
buildout.cfg
setup.py
blockdiagcontrib/__init__.py
blockdiagcontrib/square.py
blockdiagcontrib_square.egg-info/PKG-INFO
blockdiagcontrib_square.egg-info/SOURCES.txt
blockdiagcontrib_square.egg-info/dependency_links.txt
blockdiagcontrib_square.egg-info/namespace_packages.txt
blockdiagcontrib_square.egg-info/requires.txt
blockdiagcontrib_square.egg-info/top_level.txt