Metadata-Version: 1.0
Name: blockdiagcontrib-square
Version: 0.1.3
Summary: noderenderer plugin for blockdiag
Home-page: http://blockdiag.com/
Author: Takeshi Komiya
Author-email: i.tkomiya at gmail.com
License: PSL
Keywords: diagram,generator
Platform: UNKNOWN
Classifier: Development Status :: 4 - Beta
Classifier: Intended Audience :: System Administrators
Classifier: License :: OSI Approved :: Python Software Foundation License
Classifier: Programming Language :: Python
Classifier: Topic :: Software Development
Classifier: Topic :: Software Development :: Documentation
Classifier: Topic :: Text Processing :: Markup
